config/__init__.py
config/asgi.py
config/settings.py
config/urls.py
config/wsgi.py
example/__init__.py
example/admin.py
example/apps.py
example/models.py
example/tests.py
example/urls.py
example/views.py
example/migrations/__init__.py
nmb/__init__.py
nmb/apps.py
nmb/payment.py
nmb/migrations/__init__.py
django_nmb-0.0.2.dist-info/LICENSE
django_nmb-0.0.2.dist-info/METADATA
django_nmb-0.0.2.dist-info/WHEEL
django_nmb-0.0.2.dist-info/top_level.txt
django_nmb-0.0.2.dist-info/RECORD
