Metadata-Version: 2.1
Name: django-nmb
Version: 0.0.2
Summary: A Django application which assist on integration of your web application with NMB BANK Merchant payment gateway with easy step
Home-page: https://github.com/devmed/django-nmb
Author: Medson Naftali
Author-email: medsonnaftal@gmail.com
License: UNKNOWN
Project-URL: Bug Tracker, https://github.com/devmed/django-nmb/issues
Platform: UNKNOWN
Classifier: Programming Language :: Python :: 3
Classifier: License :: OSI Approved :: MIT License
Classifier: Operating System :: OS Independent
License-File: LICENSE
